<annotation>
    <folder>C:\Users\rdc872\D_Drive\Special.FOLDER\School\Masters\Classes\CMPT898\annotations\img_png</folder>
    <filename>40_G0428528_3.png</filename>
    <path>C:\Users\rdc872\D_Drive\Special.FOLDER\School\Masters\Classes\CMPT898\annotations\img_png\40_G0428528_3.png</path>
    <source>
        <database>annotations</database>
    </source>
    <size>
        <width>4000</width>
        <height>500</height>
        <depth>3</depth>
    </size>
    <segmented>0</segmented>
    <object>
        <name>plant</name>
        <pose>Unspecified</pose>
        <truncated>0</truncated>
        <difficult>0</difficult>
        <bndbox>
            <xmin>0</xmin>
            <ymin>225</ymin>
            <xmax>36</xmax>
            <ymax>275</ymax>
        </bndbox>
    </object>
    <object>
        <name>plant</name>
        <pose>Unspecified</pose>
        <truncated>0</truncated>
        <difficult>0</difficult>
        <bndbox>
            <xmin>61</xmin>
            <ymin>219</ymin>
            <xmax>109</xmax>
            <ymax>264</ymax>
        </bndbox>
    </object>
    <object>
        <name>plant</name>
        <pose>Unspecified</pose>
        <truncated>0</truncated>
        <difficult>0</difficult>
        <bndbox>
            <xmin>113</xmin>
            <ymin>236</ymin>
            <xmax>156</xmax>
            <ymax>277</ymax>
        </bndbox>
    </object>
    <object>
        <name>plant</name>
        <pose>Unspecified</pose>
        <truncated>0</truncated>
        <difficult>0</difficult>
        <bndbox>
            <xmin>183</xmin>
            <ymin>229</ymin>
            <xmax>214</xmax>
            <ymax>259</ymax>
        </bndbox>
    </object>
    <object>
        <name>plant</name>
        <pose>Unspecified</pose>
        <truncated>0</truncated>
        <difficult>0</difficult>
        <bndbox>
            <xmin>355</xmin>
            <ymin>245</ymin>
            <xmax>384</xmax>
            <ymax>279</ymax>
        </bndbox>
    </object>
    <object>
        <name>plant</name>
        <pose>Unspecified</pose>
        <truncated>0</truncated>
        <difficult>0</difficult>
        <bndbox>
            <xmin>449</xmin>
            <ymin>233</ymin>
            <xmax>486</xmax>
            <ymax>269</ymax>
        </bndbox>
    </object>
    <object>
        <name>plant</name>
        <pose>Unspecified</pose>
        <truncated>0</truncated>
        <difficult>0</difficult>
        <bndbox>
            <xmin>489</xmin>
            <ymin>229</ymin>
            <xmax>499</xmax>
            <ymax>260</ymax>
        </bndbox>
    </object>
</annotation>
