<annotation>
    <folder>D:\tensorflow\projects\PlantClumpDetection\git\datasets\annotations\img_patches_8_png</folder>
    <filename>7_G0428457_0.png</filename>
    <path>D:\tensorflow\projects\PlantClumpDetection\git\datasets\annotations\img_patches_8_png\7_G0428457_0.png</path>
    <source>
        <database>annotations</database>
    </source>
    <size>
        <width>500</width>
        <height>500</height>
        <depth>3</depth>
    </size>
    <segmented>0</segmented>
    <object>
        <name>clumped</name>
        <pose>Unspecified</pose>
        <truncated>0</truncated>
        <difficult>0</difficult>
        <bndbox>
            <xmin>239</xmin>
            <ymin>149</ymin>
            <xmax>382</xmax>
            <ymax>199</ymax>
        </bndbox>
    </object>
    <object>
        <name>isolated</name>
        <pose>Unspecified</pose>
        <truncated>0</truncated>
        <difficult>0</difficult>
        <bndbox>
            <xmin>41</xmin>
            <ymin>151</ymin>
            <xmax>94</xmax>
            <ymax>186</ymax>
        </bndbox>
    </object>
    <object>
        <name>isolated</name>
        <pose>Unspecified</pose>
        <truncated>0</truncated>
        <difficult>0</difficult>
        <bndbox>
            <xmin>157</xmin>
            <ymin>165</ymin>
            <xmax>200</xmax>
            <ymax>202</ymax>
        </bndbox>
    </object>
    <object>
        <name>isolated</name>
        <pose>Unspecified</pose>
        <truncated>0</truncated>
        <difficult>0</difficult>
        <bndbox>
            <xmin>200</xmin>
            <ymin>158</ymin>
            <xmax>236</xmax>
            <ymax>194</ymax>
        </bndbox>
    </object>
    <object>
        <name>isolated</name>
        <pose>Unspecified</pose>
        <truncated>0</truncated>
        <difficult>0</difficult>
        <bndbox>
            <xmin>451</xmin>
            <ymin>163</ymin>
            <xmax>484</xmax>
            <ymax>187</ymax>
        </bndbox>
    </object>
    <object>
        <name>isolated</name>
        <pose>Unspecified</pose>
        <truncated>0</truncated>
        <difficult>0</difficult>
        <bndbox>
            <xmin>485</xmin>
            <ymin>165</ymin>
            <xmax>499</xmax>
            <ymax>202</ymax>
        </bndbox>
    </object>
</annotation>
